{"wordsByLength": [{"length": 19, "words": ["auriculoventricular"]}, {"length": 18, "words": ["anthropogeographer", "astragalonavicular"]}, {"length": 17, "words": ["abdominoposterior", "acromioclavicular", "algoesthesiometer", "antiparliamenteer", "archlexicographer", "astrophotographer"]}, {"length": 16, "words": ["abdominoanterior", "architypographer", "archsacrificator", "atrioventricular", "autolithographer"]}, {"length": 15, "words": ["acromioscapular", "anesthesiometer", "anteroposterior", "anticrepuscular", "archconspirator", "archphilosopher", "astrophotometer", "autographometer", "autoregenerator", "autotransformer"]}, {"length": 14, "words": ["absorptiometer", "acetonurometer", "acupuncturator", "agrostographer", "algesireceptor", "amphiprostylar", "anacamptometer", "anesthesimeter", "antejentacular", "anteroinferior", "anterointerior", "anterosuperior", "antiamboceptor", "anticoagulator", "anticovenanter", "antifertilizer", "antioxygenator", "antipeduncular", "antisensitizer", "antistadholder", "antitrochanter", "antitubercular", "antivaccinator", "antivermicular", "archchronicler", "archdepredator", "archdissembler", "archipresbyter", "archsacrificer", "archworkmaster", "arteriopressor", "assmannshauser", "astigmatometer", "astronavigator", "augmentationer", "autobiographer", "autocollimator"]}, {"length": 13, "words": ["accelerometer", "achromobacter", "adhesivemeter", "administrator", "aerotonometer", "affenpinscher", "albertustaler", "albuminimeter", "albuminometer", "alcoholimeter", "alcoholometer", "alcovinometer", "algiomuscular", "anaesthetizer", "anathematiser", "anathematizer", "angelographer", "anterioyancer", "anthracometer", "anthropolater", "anthropometer", "antiballooner", "anticatalyzer", "anticonductor", "antiepicenter", "antilacrosser", "antimissioner", "antiresonator", "antireticular", "apophorometer", "archcorrupter", "archcupbearer", "archdisturber", "archflatterer", "archmessenger", "archplunderer", "archpresbyter", "archpretender", "archtreasurer", "arterioverter", "astrologaster", "attitudiniser", "attitudinizer", "authenticator", "autoconverter", "autonavigator"]}, {"length": 12, "words": ["abrasiometer", "acclimatiser", "acclimatizer", "accommodator", "accomplisher", "achtelthaler", "acinotubular", "acknowledger", "acutiplantar", "adenographer", "admonitioner", "adstipulator", "aeolsklavier", "afterthinker", "agglomerator", "agglutinator", "agriculturer", "airfreighter", "albumeniizer", "alcoholmeter", "algesiometer", "allegorister", "alpenstocker", "alphabetiser", "alphabetizer", "ambisinister", "americanizer", "amoebobacter", "amphitheater", "amplificator", "anakinetomer", "andropetalar", "anesthetizer", "animadverter", "antesuperior", "antheximeter", "anthologizer", "anticourtier", "antidiffuser", "antimacassar", "antioxidizer", "antireformer", "antisalooner", "antisplasher", "antispreader", "antivibrator", "aplanobacter", "apomecometer", "appendicular", "appropriator", "approximator", "arbalestrier", "archaeolater", "archaeologer", "archagitator", "archconsoler", "archdeceiver", "archdefender", "archengineer", "archgovernor", "archinformer", "archminister", "archmurderer", "archoverseer", "archpilferer", "archswindler", "arcubalister", "argentometer", "argumentator", "arithmometer", "arminianizer", "armourbearer", "arteriometer", "arteriomotor", "assassinator", "astigmatizer", "astigmometer", "astrographer", "attemperator", "autodetector", "averruncator"]}, {"length": 11, "words": ["abarticular", "abbreviator", "aberrometer", "aberuncator", "abjudicator", "abumbrellar", "accelerator", "accentuator", "accessioner", "accompanier", "accumulator", "acetobacter", "achtehalber", "actinometer", "acutangular", "adaptometer", "adjudicator", "adminicular", "adpromissor", "adulterator", "adumbrellar", "aerographer", "affreighter", "afterburner", "aftercareer", "aftercooler", "afterdinner", "aftermatter", "aftersupper", "aggrandiser", "aggrandizer", "aigialosaur", "airworthier", "albedometer", "albumeniser", "albumenizer", "albumimeter", "alchemister", "aleurometer", "algesimeter", "alivincular", "alkalimeter", "allegoriser", "allegorizer", "alliterator", "amalgamater", "amalgamator", "ambassadeur", "amebobacter", "amelanchier", "ameliorator", "ametrometer", "amortisseur", "amperemeter", "amperometer", "amphistylar", "ampitheater", "amsterdamer", "anapnometer", "angelolater", "angulometer", "animalcular", "annihilator", "annunciator", "antagonizer", "antechamber", "antiangular", "antiburgher", "antichamber", "anticheater", "anticipator", "anticreator", "anticreeper", "antiemperor", "antiguggler", "antimasquer", "antipopular", "antirattler", "antireducer", "antisnapper", "antistriker", "antitruster", "apertometer", "applegrower", "applemonger", "apportioner", "appreciator", "apprehender", "arbitrageur", "arborolater", "archbotcher", "archbuilder", "archcheater", "archcorsair", "archcozener", "archdapifer", "archemperor", "archfounder", "archicantor", "archigaster", "archleveler", "archplotter", "archseducer", "archtempter", "archtraitor", "archvisitor", "areographer", "arkansawyer", "armorbearer", "aromatophor", "arquebusier", "arthrometer", "articulator", "ascertainer", "asphyxiator", "assecurator", "assimilator", "astromancer", "ataxiameter", "atmidometer", "auscultator", "autochanger", "autocoherer", "autographer", "autostarter", "autotheater", "autotractor", "autoxidator", "autoxidizer", "auxanometer", "azotobacter"]}, {"length": 10, "words": ["abominator", "absolvitor", "abstracter", "abstractor", "accersitor", "accipenser", "acclamator", "accoucheur", "acensuador", "acequiador", "acetabular", "acetylator", "acetylizer", "acetimeter", "acetometer", "acidimeter", "acidometer", "acouometer", "acquiescer", "acquisitor", "adipometer", "admeasurer", "administer", "admittatur", "admonisher", "adventurer", "advertiser", "advertizer", "aerobacter", "aeromancer", "aeroplaner", "aestivator", "affrighter", "aflagellar", "africander", "afrikander", "aftercomer", "afterrider", "aggravator", "aggregator", "agricultor", "alablaster", "alleviater", "alleviator", "alloisomer", "allwhither", "almacantar", "almucantar", "alternater", "alternator", "altogether", "ambassador", "ambidexter", "amboceptor", "ambodexter", "ambulancer", "ambuscader", "amylometer", "ammonifier", "amphiaster", "amphimacer", "anatomiser", "anatomizer", "anemometer", "angiometer", "angledozer", "anglemeter", "anywhither", "ankylosaur", "annoyancer", "antecessor", "antennifer", "antennular", "antenumber", "anteocular", "anthochlor", "anticancer", "antifouler", "antiliquor", "antilitter", "antimartyr", "antimasker", "antimatter", "antimerger", "antiphoner", "antiprimer", "antirenter", "antistater", "antithenar", "aphorismer", "apologiser", "apologizer", "applicator", "approacher", "approbator", "aqualunger", "aquaplaner", "aquatinter", "araeometer", "arbalester", "arbalister", "arbitrager", "arbitrator", "arbuscular", "archgunner", "archleader", "archlecher", "archmocker", "archpastor", "archpillar", "archplayer", "archrobber", "archworker", "arenicolor", "argoletier", "aromatiser", "aromatizer", "arrendator", "arteriolar", "assentator", "associator", "asssembler", "astonisher", "astragalar", "astrogator", "astrolater", "astrologer", "astrometer", "astronomer", "atrabiliar", "attenuator", "attestator", "attributer", "attributor", "auctioneer", "audiencier", "audiometer", "austringer", "authoriser", "authorizer", "autocamper", "autocrator", "autodialer", "autoheader", "autojigger", "autokrator", "autoloader", "autosender", "autostoper", "auxiliator", "axebreaker", "azotometer"]}, {"length": 9, "words": ["abandoner", "abdicator", "aberrator", "abnegator", "abolisher", "abreuvoir", "abrogator", "absconder", "absoluter", "abstainer", "abstruser", "acapsular", "accipiter", "acclaimer", "accounter", "accusator", "acellular", "acetifier", "acidifier", "acipenser", "acoumeter", "acquereur", "acquitter", "acrometer", "activator", "acuductor", "acusector", "acutiator", "adamastor", "addresser", "addressor", "adelaster", "adjutator", "admirator", "admonitor", "adulterer", "advocator", "aerometer", "aeromotor", "aeronomer", "affiancer", "afflicter", "affronter", "afrikaner", "aggressor", "agistator", "agrimotor", "airmarker", "airmonger", "airometer", "airplaner", "alabaster", "aleconner", "alemonger", "aletaster", "alexander", "algometer", "alienator", "alimenter", "alkaliser", "alkalizer", "allegator", "alliancer", "alligator", "allocator", "allocatur", "alluminor", "almogavar", "almsgiver", "alnaschar", "altimeter", "altometer", "alzheimer", "ambulator", "amplifier", "amputator", "anangular", "ancienter", "angetenar", "animalier", "anywither", "annotater", "annotator", "announcer", "annueller", "antechoir", "antichlor", "antilabor", "antimeter", "antipolar", "antiracer", "antirumor", "antisolar", "antitumor", "antocular", "aphidozer", "aphoriser", "aphorizer", "apocenter", "apparitor", "appeacher", "appetiser", "appetizer", "applauder", "appointer", "appointor", "appraiser", "appressor", "appreteur", "aquameter", "arborator", "archaiser", "archaizer", "archiater", "archruler", "archsewer", "archurger", "areasoner", "arendator", "areometer", "arianizer", "arpenteur", "arraigner", "arrogator", "arsnicker", "articular", "artificer", "artolater", "ascenseur", "aspersoir", "asphalter", "aspirator", "assaulter", "assembler", "astatizer", "astringer", "atmolyzer", "atmometer", "atrabilar", "attainder", "attempter", "attracter", "attractor", "audiencer", "audiviser", "augmenter", "augmentor", "auricular", "auslander", "austemper", "autocoder", "autolater", "automaker", "automotor", "automower", "autopolar", "autoriser", "autotimer", "auxofluor", "auxometer", "avalvular", "avascular", "avuncular", "awkwarder", "axbreaker", "axemaster", "axminster", "azobacter"]}, {"length": 8, "words": ["abatjour", "abattoir", "abductor", "abhorrer", "abounder", "abridger", "abrupter", "absenter", "absolver", "absorber", "absurder", "accensor", "accentor", "accepter", "acceptor", "accessor", "accipter", "accorder", "accouter", "accumber", "achatour", "achernar", "achiever", "acicular", "acounter", "acquirer", "actifier", "actioner", "actuator", "adductor", "adjoiner", "adjudger", "adjuster", "adjustor", "admitter", "adnumber", "adroiter", "adsessor", "adulator", "advancer", "aerophor", "aetosaur", "affecter", "affector", "affeerer", "affeeror", "affirmer", "affrayer", "aflicker", "aflutter", "afteroar", "afterwar", "agitator", "aglimmer", "aglitter", "agonizer", "airliner", "aisteoir", "akhissar", "akmuddar", "alastair", "alcalzar", "allosaur", "allotter", "almander", "almanner", "altincar", "alveolar", "amaister", "ambusher", "amitular", "amoinder", "amounter", "ampullar", "amritsar", "analyser", "analyzer", "anatifer", "anaunter", "ancestor", "anchorer", "anicular", "animater", "animator", "annealer", "annueler", "annuller", "anointer", "anovular", "answerer", "anteater", "anterior", "antiager", "anticker", "antiquer", "antiwear", "anvasser", "apicilar", "apicular", "apologer", "appealer", "appearer", "appeaser", "appellor", "appender", "appriser", "apprizer", "approver", "aproneer", "aquarter", "arbitrer", "archiver", "archliar", "argenter", "argufier", "armchair", "armourer", "arranger", "arrector", "arrester", "arrestor", "artiller", "ascender", "ascensor", "ashimmer", "aslumber", "asmolder", "asperger", "asperser", "aspersor", "assailer", "assenter", "assentor", "asserter", "assertor", "assessor", "assigner", "assignor", "assister", "assistor", "assorter", "assuager", "atheizer", "atomizer", "attacher", "attacker", "attainer", "attainor", "attemper", "attender", "attester", "attestor", "atwitter", "auguster", "aumildar", "auntlier", "austerer", "auxiliar", "averager", "avicular", "avigator", "avoucher", "awakener", "aweather", "awfuller", "axhammer", "axmaster", "axometer"]}, {"length": 7, "words": ["abactor", "abaiser", "abetter", "abettor", "abiezer", "abjurer", "ablator", "aborter", "abrader", "abraser", "abutter", "acceder", "accruer", "accuser", "accusor", "acerber", "acrider", "acroter", "adapter", "adaptor", "additur", "adducer", "adepter", "adherer", "adjiger", "adjurer", "adjuror", "adjutor", "admirer", "adopter", "adorner", "adulter", "adviser", "advisor", "advoyer", "aerator", "aerocar", "affixer", "aflower", "aginner", "agister", "agistor", "aguador", "ajitter", "akmudar", "akroter", "aladfar", "alaster", "alastor", "alcazar", "alerter", "algebar", "aliener", "alienor", "aligner", "aliofar", "alisier", "alister", "allayer", "alleger", "allobar", "allover", "allower", "allurer", "almemar", "almemor", "almoner", "alnager", "alquier", "alterer", "amasser", "amateur", "amchoor", "amender", "amercer", "amildar", "amintor", "amlikar", "ammeter", "amutter", "ananter", "angolar", "angrier", "angster", "angular", "anither", "annexer", "annoyer", "annular", "annuler", "another", "antenor", "antewar", "anticar", "anticor", "antiwar", "antsier", "anunder", "apiator", "applier", "apposer", "aquafer", "aquifer", "aquiver", "arbiter", "arborer", "areolar", "armiger", "armorer", "arouser", "arrayer", "arriver", "ashiver", "asimmer", "aslaver", "aspirer", "assayer", "assamar", "asseour", "assever", "assewer", "assizer", "assumer", "assurer", "assuror", "astylar", "astrier", "asunder", "atafter", "ateeter", "atelier", "athanor", "athenor", "attirer", "aucaner", "auditor", "augerer", "augurer", "autocar", "availer", "avenger", "averrer", "averter", "aviador", "aviator", "avoider", "avouter", "avowter", "awaiter", "awarder", "awonder", "axillar", "axmaker", "azofier"]}, {"length": 6, "words": ["abaser", "abater", "abator", "abider", "abuser", "acamar", "acater", "acheer", "achier", "achter", "acider", "acinar", "acuter", "adorer", "adular", "aequor", "aerier", "aether", "affair", "affeer", "affeir", "afshar", "agreer", "airier", "aissor", "alazor", "alegar", "aleger", "aliner", "aliter", "almner", "altair", "alular", "amazer", "ambeer", "ambier", "ambler", "amober", "amobyr", "ampler", "amuser", "anchor", "angler", "anomer", "answer", "anther", "antiar", "antjar", "antler", "apolar", "appair", "appear", "arbour", "archer", "ardour", "arguer", "arider", "ariser", "armour", "arrear", "arthur", "artier", "ascher", "aselar", "ashier", "ashlar", "ashler", "asmear", "asteer", "astrer", "atazir", "atoner", "atterr", "attour", "auctor", "aulder", "aunter", "aushar", "auster", "auteur", "author", "avatar", "avener", "avoyer", "avower", "avshar", "awater", "awshar"]}, {"length": 5, "words": ["abear", "aberr", "abhor", "abkar", "abler", "abner", "abstr", "accur", "achar", "acher", "achor", "acier", "acker", "actor", "adder", "adzer", "aeger", "aegir", "aesir", "afear", "after", "agger", "aggur", "aider", "aiger", "aimer", "airer", "aiver", "ajhar", "alcor", "alder", "alfur", "algor", "aller", "altar", "alter", "alvar", "ambar", "amber", "ameer", "amhar", "ammer", "amour", "amper", "ancor", "andor", "anear", "anger", "angor", "anker", "anour", "ansar", "anser", "antar", "apair", "appar", "apter", "arber", "arbor", "arder", "ardor", "arear", "arhar", "armer", "armor", "aroar", "artar", "arter", "asher", "ashir", "ashur", "askar", "asker", "asper", "aster", "astir", "astor", "astur", "athar", "atour", "attar", "atter", "auger", "augur", "aurar", "aurir", "autor", "avoir", "avour", "awber", "awhir", "awner"]}, {"length": 4, "words": ["abbr", "abir", "acer", "acor", "adar", "addr", "ador", "afar", "afer", "agar", "ager", "ahir", "aivr", "ajar", "aker", "alar", "alur", "amar", "amir", "amor", "apar", "aper", "arar", "askr", "asor", "astr", "atar", "avar", "aver", "axer"]}, {"length": 3, "words": ["abr", "aer", "agr", "air", "aor", "apr", "arr"]}, {"length": 2, "words": ["ar"]}]}