{"wordsByLength": [{"length": 19, "words": ["electrometallurgist", "electrophysiologist", "electrotechnologist", "electrotherapeutist"]}, {"length": 18, "words": ["electroluminescent"]}, {"length": 17, "words": ["electrothermostat", "ethnomusicologist"]}, {"length": 16, "words": ["electrobiologist", "electromagnetist", "electrophysicist", "electrotherapist", "embourgeoisement", "environmentalist", "epidemiographist", "epiphenomenalist", "epistolographist", "erythrocytoblast"]}, {"length": 15, "words": ["eclaircissement", "effranchisement", "emancipationist", "endocrinologist", "endodontologist", "enfranchisement", "equiprobabilist", "experientialist", "experimentalist", "exploitationist"]}, {"length": 14, "words": ["ecclesiologist", "eclairissement", "educationalist", "electrochemist", "electrodeposit", "encyclopaedist", "encyclopediast", "engrandizement", "epidemiologist", "epileptologist", "epistemologist", "equiomnipotent", "examinationist", "excitonutrient", "existentialist", "expergefacient", "extinguishment", "extirpationist"]}, {"length": 13, "words": ["ectomesoblast", "electrologist", "electromagnet", "electrotypist", "electrovalent", "embarrassment", "embellishment", "embranglement", "embreathement", "embrittlement", "emigrationist", "enbranglement", "encyclopedist", "encompassment", "encorbellment", "encouragement", "enlightenment", "ensorcellment", "enterrologist", "entertainment", "entosthoblast", "entozoologist", "epigrammatist", "epithalamiast", "equidifferent", "equilibristat", "equiponderant", "eschatologist", "esperantidist", "establishment", "esthesioblast", "ethnobotanist", "ethnographist", "ethnolinguist", "etruscologist", "exacerbescent", "excavationist", "excommunicant", "exhibitionist", "expeditionist", "experimentist", "expressionist", "exteroceptist", "extinctionist", "extinguishant", "extramoralist"]}, {"length": 12, "words": ["echinologist", "econometrist", "editorialist", "educationist", "effervescent", "efflorescent", "egyptologist", "electronvolt", "elementalist", "elementarist", "elocutionist", "emanationist", "emancipatist", "embattlement", "embezzlement", "embitterment", "emblazonment", "embouchement", "embranchment", "embreastment", "embryologist", "emotionalist", "empeoplement", "empiercement", "empoisonment", "empressement", "encastrement", "enchainement", "enchancement", "encipherment", "encirclement", "encoffinment", "encorbelment", "encroachment", "encumberment", "endamagement", "endangerment", "energeticist", "enfeeblement", "engenderment", "enravishment", "enshrinement", "enswathement", "entanglement", "enteropneust", "enthrallment", "enthronement", "entomolegist", "entomologist", "entomotomist", "entrancement", "entrenchment", "entreprenant", "envisagement", "envisionment", "enzymologist", "equidominant", "erectopatent", "erythroblast", "erpetologist", "eruditionist", "escapologist", "essentialist", "estrangement", "evolutionist", "excandescent", "exclusionist", "excursionist", "executionist", "exemptionist", "exobiologist", "exorcisement", "exorcizement", "expansionist", "expedientist", "explosionist", "expulsionist", "extensionist", "extortionist"]}, {"length": 11, "words": ["easternmost", "echelonment", "eclecticist", "ecroulement", "ecumenicist", "electragist", "electrogilt", "electropult", "electrotest", "emblematist", "emboitement", "emboltement", "embouchment", "embowelment", "embowerment", "embracement", "embroilment", "empanelment", "emparchment", "empiecement", "emplacement", "emplanement", "empowerment", "empressment", "enamourment", "enchainment", "enchantment", "enclavement", "encrownment", "encrustment", "endodontist", "endorsement", "endoscopist", "enfeoffment", "enfoeffment", "enforcement", "enframement", "englobement", "engorgement", "engraftment", "engrailment", "engravement", "engrossment", "enhancement", "enjambement", "enlargement", "enlivenment", "enlodgement", "ennoblement", "enouncement", "enplanement", "enslavement", "ensnarement", "entablement", "enthralment", "entitlement", "entrainment", "entreatment", "entrustment", "entwinement", "envelopment", "environment", "eosinoblast", "epigenesist", "epigraphist", "equationist", "equidistant", "equilibrant", "equilibrist", "equipendent", "equipollent", "equivaliant", "erupturient", "escheatment", "esotericist", "esperantist", "espousement", "estrepement", "ethnogenist", "ethnologist", "etymologist", "eudaemonist", "eudaimonist", "evanishment", "exclusivist", "exconjugant", "expectorant", "explorement", "expungement", "exterminist", "externalist", "extravagant", "extraviolet"]}, {"length": 10, "words": ["earthliest", "earthlight", "eastermost", "eboulement", "ecclesiast", "edaphodont", "effacement", "eyeservant", "elaeoblast", "elaioplast", "elargement", "electrojet", "eloignment", "emancipist", "embalmment", "embankment", "embargoist", "embarkment", "embodiment", "embonpoint", "embossment", "emotionist", "empalement", "empiricist", "employment", "emportment", "enablement", "enamellist", "enamorment", "encampment", "encasement", "encashment", "encystment", "encodement", "encrotchet", "encrustant", "endearment", "enfacement", "enfoldment", "engagement", "engouement", "engulfment", "enigmatist", "enjambment", "enjoinment", "enlacement", "enlevement", "enlinkment", "enlistment", "enmeshment", "ennoblment", "enragement", "enregiment", "enrichment", "enrobement", "enrockment", "enrollment", "enserfment", "ensignment", "entailment", "entassment", "entelodont", "enterocyst", "enthusiast", "enticement", "entoilment", "entombment", "entonement", "entrapment", "enviroment", "enwrapment", "eoghanacht", "epaulement", "ephemerist", "ephererist", "episcopant", "epistolist", "epitaphist", "equijacent", "equilucent", "equiparant", "equipotent", "equisonant", "equivalent", "ergatocrat", "ergonomist", "erosionist", "erubescent", "esbatement", "escapement", "escarpment", "escortment", "espacement", "essoinment", "eternalist", "ethologist", "etiologist", "eudemonist", "eugenicist", "euhemerist", "euphoriant", "evanescent", "evangelist", "evincement", "evolvement", "excystment", "excitement", "excrescent", "excuderunt", "exercitant", "exhibitant", "exhilarant", "exodontist", "exorbitant", "expediment", "experiment", "extollment", "extractant", "extrospect", "extuberant"]}, {"length": 9, "words": ["earthfast", "earthiest", "eastabout", "ebullient", "ecdysiast", "eclectist", "ecologist", "ecomomist", "economist", "ectoblast", "ectoproct", "ecumenist", "edificant", "educement", "efficient", "effodient", "effulgent", "ehatisaht", "eyebright", "ejectment", "elaterist", "elderwort", "eleoblast", "eleoplast", "eliminant", "eliphalet", "eloinment", "elopement", "emanatist", "embayment", "embarment", "embedment", "emblement", "emblemist", "embowment", "emollient", "emolument", "enactment", "enamelist", "encomiast", "encoronet", "endoblast", "endoplast", "endoproct", "endowment", "enduement", "engallant", "engarment", "engoument", "enjoyment", "enologist", "enrolment", "entempest", "enterfeat", "entoblast", "entoproct", "entrechat", "enwrought", "epigenist", "epilogist", "epistolet", "epitomist", "eponymist", "epopoeist", "equipment", "equvalent", "eradicant", "erasement", "eroticist", "esoterist", "essenhout", "estaminet", "estradiot", "ethnicist", "eucharist", "euphemist", "euthenist", "evenlight", "exactment", "exaltment", "examinant", "exarchist", "excellent", "exceptant", "excipient", "excrement", "excurrent", "executant", "exegesist", "exegetist", "exilement", "exoticist", "expectant", "expedient", "expellant", "expellent", "experient", "expiatist", "explement", "explodent", "exsiccant", "exsurgent", "extolment", "extradict", "extraught", "extravert", "extremest", "extremist", "extrovert", "exuberant"]}, {"length": 8, "words": ["eagerest", "earliest", "earthnut", "earthset", "easement", "eastmost", "echeloot", "eckehart", "ectocyst", "eddyroot", "edgeshot", "efferent", "effluent", "eggfruit", "eggplant", "eyelight", "eyepoint", "eyesight", "ejicient", "electant", "electret", "elegiast", "elephant", "eloquent", "elsewhat", "embright", "emergent", "emigrant", "emittent", "empacket", "empocket", "emptiest", "emulgent", "enascent", "enclaret", "endocyst", "endpoint", "endsheet", "endurant", "energist", "enforest", "ennuyant", "ensilist", "enspirit", "entalent", "entocyst", "entrepot", "enturret", "epiblast", "epiproct", "epochist", "epoptist", "equalist", "equidist", "equitant", "equitist", "ergostat", "ergotist", "errorist", "erumpent", "escapist", "escargot", "eschalot", "esculent", "esparcet", "essayist", "essaylet", "essorant", "esurient", "ethernet", "ethicist", "eucalypt", "eugenist", "eulogist", "euphuist", "evacuant", "evectant", "evelight", "evillest", "evolvent", "exactest", "excedent", "excitant", "excubant", "exercent", "exhalant", "exhalent", "exigeant", "existant", "existent", "exorcist", "expirant", "explicit", "exponent", "exscript", "exsecant", "exstruct", "externat", "extromit", "exultant"]}, {"length": 7, "words": ["earnest", "earshot", "earwort", "easiest", "ebonist", "echoist", "edgiest", "eelboat", "eeliest", "eelpout", "eeriest", "effront", "eggment", "egotist", "eyebolt", "eyelast", "eyeroot", "eyeshot", "eyespot", "eyewort", "elegant", "elegist", "element", "elfwort", "eligent", "elitist", "elliott", "elmiest", "elohist", "emanant", "emanent", "emerant", "emicant", "eminent", "empight", "emprent", "emprint", "emulant", "enatant", "enceint", "enchant", "encheat", "enchest", "encrypt", "encrust", "endmost", "endoubt", "engraft", "enhaunt", "enheart", "enherit", "enlight", "enosist", "enright", "ensaint", "ensient", "ensuant", "entrant", "entreat", "entrept", "entrust", "entwist", "envault", "enwrapt", "eobiont", "epaulet", "epeeist", "epicist", "epiglot", "epithet", "eranist", "erodent", "escheat", "escopet", "escript", "estafet", "estreat", "estuant", "etacist", "etatist", "etchant", "etiquet", "evenest", "everest", "everett", "evident", "evilest", "excerpt", "excheat", "excudit", "exedent", "exflect", "exhaust", "exhibit", "exigent", "exodist", "explait", "explant", "exploit", "exposit", "extinct", "extract", "extrait", "extreat", "extruct", "exultet"]}, {"length": 6, "words": ["eaglet", "earlet", "edplot", "eelpot", "effect", "effort", "efreet", "eftest", "egbert", "egghot", "egoist", "egriot", "eyalet", "eident", "eydent", "eyedot", "eyelet", "eyepit", "eyrant", "elanet", "elbert", "eldest", "elegit", "elicit", "elliot", "eltrot", "eluant", "eluent", "embost", "emerit", "emmett", "empest", "emunct", "encist", "encyst", "endebt", "endent", "endict", "enfant", "enfect", "enfort", "engirt", "englut", "enhort", "enlist", "enmist", "enoint", "enrapt", "enroot", "enseat", "epirot", "epoist", "equant", "equipt", "ernest", "errant", "erudit", "escort", "escout", "esprit", "essart", "eudist", "evomit", "except", "excyst", "excoct", "exempt", "exeunt", "exhort", "expect", "expert", "explat", "export", "exsect", "exsert", "extant", "extent", "extort"]}, {"length": 5, "words": ["ebbet", "ecart", "eclat", "edict", "educt", "effet", "egest", "egypt", "egret", "eight", "eyght", "eject", "elect", "eleut", "eliot", "elvet", "emmet", "enact", "enapt", "enent", "enhat", "enrut", "epact", "epist", "eplot", "epopt", "erect", "erept", "ergot", "ermit", "ernst", "eruct", "erupt", "escot", "event", "evert", "evict", "ewest", "exact", "exalt", "exeat", "exect", "exert", "exist", "exopt", "expdt", "exult", "exust"]}, {"length": 4, "words": ["east", "echt", "edit", "eyot", "emit", "empt", "epit", "eqpt", "erat", "erst", "exit", "expt"]}, {"length": 3, "words": ["eat", "eft", "elt", "est", "ext"]}, {"length": 2, "words": ["et"]}]}