{"wordsByLength": [{"length": 19, "words": ["gastroalbuminorrhea"]}, {"length": 17, "words": ["gastroblennorrhea", "gastrohyperneuria", "ginglymoarthrodia"]}, {"length": 16, "words": ["gastroenteralgia", "gastrohydrorrhea", "gastroperiodynia", "gastrosuccorrhea"]}, {"length": 15, "words": ["gastromyxorrhea", "glossocarcinoma"]}, {"length": 14, "words": ["gangliasthenia", "ganglioneuroma", "gastroatrophia", "gnathobdellida", "graptolitoidea"]}, {"length": 13, "words": ["galactorrhoea", "gasterotricha", "gastrasthenia", "gastratrophia", "gastromalacia", "gastrorrhagia", "generalissima", "gephyrophobia", "germanophobia", "gerontophilia", "geumatophobia", "gigantomachia", "gigantostraca", "gynaecomastia", "ginglymostoma", "gynostemiumia", "gloiosiphonia", "gnathostomata", "gorgoneioneia", "graptolithida", "graptolithina", "gregarinoidea"]}, {"length": 12, "words": ["galactohemia", "galactorrhea", "galactosemia", "galactosuria", "gametophagia", "gametophobia", "gasterotheca", "gastraneuria", "gastrectasia", "gastroatonia", "gastrochaena", "gastroptosia", "gastrotricha", "geoaesthesia", "geometroidea", "germanomania", "gymnoblastea", "gymnolaemata", "gymnostomata", "gymnostomina", "gynecomastia", "gynoeciumcia", "gynostegigia", "gyrencephala", "glaucionetta", "glycolylurea", "globicephala", "globulinuria", "glossiphonia", "glossophytia", "glossophobia", "glossoplegia", "glossoscopia", "gonopodpodia", "graphophobia", "graptoloidea", "gregarinaria", "gringophobia"]}, {"length": 11, "words": ["gaylussacia", "galactopyra", "gallophobia", "gangliomata", "ganocephala", "gasteralgia", "gasteropoda", "gastrodynia", "gastromenia", "gastrorrhea", "gastrotheca", "geissorhiza", "gelsemiumia", "gentianella", "gymnocerata", "gymnoglossa", "gymnophiona", "gymnophobia", "gynecomania", "gynecomazia", "gingivalgia", "glaucosuria", "glycyrrhiza", "glycohaemia", "glycosaemia", "glyptotheca", "gliriformia", "globigerina", "glochchidia", "glossodynia", "glossolalia", "glossopetra", "glossophaga", "glossophora", "glucosaemia", "gnathostoma", "gnathotheca", "gobernadora", "gorgoniacea", "gospodipoda", "graecomania", "grandiflora", "granulomata", "graphomania", "graphorrhea", "graptolitha", "gregarinida", "gregarinina", "grihyasutra", "gryllotalpa", "gristhorbia", "grossularia", "gubernacula"]}, {"length": 10, "words": ["gaillardia", "galactemia", "galacturia", "gallimatia", "gallomania", "gamasoidea", "gametangia", "gamophagia", "gangliglia", "gastralgia", "gastropoda", "gaultheria", "geadephaga", "geissoloma", "genipapada", "genophobia", "geometrina", "gerodermia", "gerodontia", "gibberella", "gymnadenia", "gymnasisia", "gymnoconia", "gymnolaema", "gymnorhina", "gynephobia", "gynethusia", "gynocardia", "gynostegia", "gynostemia", "gypsophila", "glagolitsa", "glycohemia", "glycopexia", "glycosemia", "glycosuria", "globularia", "gloeocapsa", "glomerella", "glossalgia", "glossocoma", "glucosemia", "glucosuria", "gnathalgia", "gnathopoda", "gondoletta", "goniotheca", "gonorrhoea", "gordioidea", "gorgonacea", "gorgonzola", "gracilaria", "gradientia", "granadilla", "grandmamma", "gravigrada", "grecomania", "grenadilla", "grinnellia", "groceteria", "guachamaca", "guignardia", "guilandina", "guptavidya"]}, {"length": 9, "words": ["gabriella", "gadolinia", "galactoma", "galinsoga", "gallicola", "gallinula", "gamomania", "gandharva", "ganglioma", "ganodonta", "gargantua", "gemmingia", "gemmipara", "generalia", "genitalia", "geodaesia", "geophagia", "georgiana", "gerocomia", "geroderma", "gigartina", "gymnotoka", "gynandria", "girandola", "gyromitra", "gyrophora", "gyrotheca", "glabbella", "glaciaria", "glauconia", "gleditsia", "glycaemia", "glochidia", "glossagra", "glucaemia", "gobioidea", "gomphrena", "gonyalgia", "goninidia", "gonytheca", "gonopodia", "gonorrhea", "gonotheca", "gordiacea", "gorgoneia", "granddada", "grandezza", "grandmama", "grandpapa", "granuloma", "granulosa", "graphiola", "gravamina", "gregarina", "gressoria", "grevillea", "grihastha", "grindelia", "guayabera", "guanabana", "guatemala", "guberniya", "guerrilla"]}, {"length": 8, "words": ["gadoidea", "galabiya", "galactia", "galagala", "galleria", "galtonia", "gambetta", "gambusia", "gammadia", "gandhara", "gandoura", "ganguela", "garapata", "garcinia", "gardenia", "garrooka", "gasteria", "gastraea", "gastrula", "gazzetta", "gelechia", "gelsemia", "gematria", "genarcha", "genetika", "genonema", "genoveva", "gentiana", "geodesia", "geophila", "geoplana", "geospiza", "geotilla", "gephyrea", "gerardia", "gerberia", "geryonia", "germania", "geropiga", "gerousia", "gesneria", "gigelira", "gigmania", "gillenia", "gymkhana", "gymnasia", "gynaecea", "gynaecia", "gyneccia", "gynoecia", "gynopara", "giornata", "giustina", "glabella", "gladiola", "glandula", "glareola", "glaucoma", "glycemia", "glyceria", "gliomata", "gloriana", "gloriosa", "glossata", "glossina", "gloxinia", "glucemia", "glumella", "gnomonia", "godmamma", "goiabada", "golconda", "golgotha", "golkakra", "gomashta", "gomontia", "gonalgia", "gonangia", "gonionia", "goniunia", "goodenia", "goodyera", "gordonia", "gorgonia", "grallina", "grandada", "grandeza", "granilla", "granzita", "gratiola", "gravilea", "gryphaea", "griselda", "guacacoa", "guapilla", "guaracha", "gubernia", "guerilla", "guerrila", "gulancha", "gulinula", "gurdwara", "guzmania"]}, {"length": 7, "words": ["gadaria", "gaffkya", "gaiassa", "galabia", "galanga", "galatea", "galbula", "galidia", "gallera", "galleta", "galusha", "gangava", "ganglia", "garetta", "garlopa", "garrafa", "garrupa", "gastrea", "gazania", "gazella", "gebanga", "gehenna", "gekkota", "gelatia", "gemmula", "genetta", "geneura", "genista", "geonoma", "georama", "georgia", "geraera", "gerbera", "gerenda", "germina", "gerusia", "gesnera", "gestura", "ghebeta", "giardia", "gigeria", "gymnura", "gynecia", "gingiva", "giraffa", "girella", "glecoma", "glomera", "glucina", "gmelina", "goasila", "goburra", "godetia", "godpapa", "golilla", "gomasta", "gomeisa", "gonagia", "gonagra", "gondola", "gonidia", "gorilla", "gospoda", "gotraja", "granada", "grandma", "grandpa", "granita", "granola", "grantha", "grantia", "granula", "gravata", "gravida", "grenada", "grimmia", "guayaba", "guajira", "gualaca", "guapena", "guarana", "guariba", "guavina", "guaxima", "guazuma", "guberla", "guereba", "guereza", "guhayna", "gummata", "gunnera", "gurjara", "guttera", "guttula"]}, {"length": 6, "words": ["gadaba", "gadaea", "galcha", "galega", "galena", "galera", "gambia", "gamdia", "gamgia", "gangsa", "gangwa", "garava", "gariba", "garrya", "garuda", "geikia", "geisha", "gelada", "gemara", "genera", "geneva", "genipa", "gerara", "gerefa", "getspa", "ghalva", "ghedda", "giarra", "gyassa", "giboia", "giddea", "gidgea", "gidyea", "gifola", "gymsia", "gynura", "gyroma", "gitana", "gyttja", "giunta", "glioma", "gliosa", "gloria", "glossa", "gnamma", "goanna", "godiva", "goetia", "gohila", "goyana", "goloka", "goonda", "gopura", "gorgia", "gramma", "grampa", "granma", "granza", "grappa", "grapta", "gratia", "grewia", "griqua", "grivna", "gromia", "grulla", "guadua", "guarea", "guglia", "guiana", "guyana", "guinea", "gurkha"]}, {"length": 5, "words": ["galea", "galga", "galla", "gamba", "gamma", "ganda", "ganga", "ganja", "gansa", "ganta", "ganza", "garua", "gatha", "gaura", "gavia", "geira", "geisa", "gemma", "genoa", "genua", "ghana", "gilia", "girba", "girja", "gisla", "glaga", "gleba", "gloea", "gluma", "goala", "gobia", "gogga", "gonia", "gonna", "gooma", "gorra", "gotha", "gotra", "gotta", "gouda", "goura", "grama", "grana", "grata", "greta", "groma", "guaba", "guaka", "guama", "guana", "guara", "guasa", "guava", "guaza", "guiba", "gumma", "gunda", "gunja", "gusla", "gutta"]}, {"length": 4, "words": ["gaea", "gaga", "gaia", "gala", "gapa", "gara", "gata", "gena", "geta", "giga", "gila", "glia", "gola", "goma", "gona", "gora", "gufa", "guha", "gula", "guna"]}, {"length": 3, "words": ["goa", "gra"]}, {"length": 2, "words": ["ga"]}]}