{"wordsByLength": [{"length": 12, "words": ["odontopteryx"]}, {"length": 11, "words": ["objurgatrix", "overcomplex"]}, {"length": 10, "words": ["oleothorax", "optomeninx", "oropharynx", "osculatrix", "otosalpinx", "overprolix"]}, {"length": 9, "words": ["obstetrix", "operatrix", "overrelax", "oxylabrax"]}, {"length": 8, "words": ["octuplex", "opopanax", "opoponax", "oreortyx", "orthodox"]}, {"length": 7, "words": ["oratrix", "outflux", "outjinx", "overfix", "overlax", "overmix", "overtax"]}, {"length": 6, "words": ["opifex", "outbox", "outfox"]}, {"length": 5, "words": ["ortyx"]}, {"length": 4, "words": ["obex", "odax", "olax", "onyx", "oryx"]}, {"length": 2, "words": ["ox"]}]}