{"wordsByLength": [{"length": 13, "words": ["quadriportico"]}, {"length": 12, "words": ["quattrocento"]}, {"length": 11, "words": ["quatrocento", "quirquincho"]}, {"length": 9, "words": ["quartetto", "quartinho", "quasimodo", "quattrino", "quebracho", "quinquino", "quintetto"]}, {"length": 8, "words": ["quaestio", "quartano", "quatrino", "quatsino", "querecho", "quintato"]}, {"length": 7, "words": ["quaitso", "quellio", "quemado", "querido", "quiteno", "quomodo"]}, {"length": 6, "words": ["quando", "quango", "quarto", "quiapo", "quinto"]}, {"length": 5, "words": ["quipo", "quito"]}, {"length": 3, "words": ["qto", "quo"]}]}